setup.cfg
setup.py
SajadK/__init__.py
SajadK.egg-info/PKG-INFO
SajadK.egg-info/SOURCES.txt
SajadK.egg-info/dependency_links.txt
SajadK.egg-info/top_level.txt