Metadata-Version: 2.1
Name: SajadK
Version: 1.2
Summary: Lib Sajad
Author: sajad
Classifier: Programming Language :: Python :: 3
